MANIFEST.in
README.txt
pypi_version.txt
requirements.txt
setup.py
test_requirements.txt
version.txt
cloudshell/__init__.py
cloudshell/recorder/__init__.py
cloudshell/recorder/__main__.py
cloudshell/recorder/bootstrap.py
cloudshell/recorder/recorder_orchestrator.py
cloudshell/recorder/file_service/__init__.py
cloudshell/recorder/file_service/file_service.py
cloudshell/recorder/model/__init__.py
cloudshell/recorder/model/base_snmp_parameters.py
cloudshell/recorder/model/snmp_record.py
cloudshell/recorder/model/snmp_v2_parameters.py
cloudshell/recorder/model/snmp_v3_parameters.py
cloudshell/recorder/snmp/__init__.py
cloudshell/recorder/snmp/snmp_orchestrator.py
cloudshell/recorder/snmp/snmp_recorder.py
cloudshell/recorder/snmp/snmp_service.py
cloudshell/recorder/tools/__init__.py
cloudshell/recorder/tools/snmp_tools.py
cloudshell_recorder.egg-info/PKG-INFO
cloudshell_recorder.egg-info/SOURCES.txt
cloudshell_recorder.egg-info/dependency_links.txt
cloudshell_recorder.egg-info/entry_points.txt
cloudshell_recorder.egg-info/requires.txt
cloudshell_recorder.egg-info/top_level.txt
tests/__init__.py
tests/integration/__init__.py
tests/integration/test_recorder.py
tests/integration/test_responses.py
tests/recorder/__init__.py
tests/recorder/test_bootstrap.py
tests/recorder/test_main.py
tests/recorder/test_recorder_orch.py
tests/recorder/file_service/__init__.py
tests/recorder/file_service/test_file_service.py
tests/recorder/model/__init__.py
tests/recorder/model/test_base_snmp_params.py
tests/recorder/model/test_snmp_record.py
tests/recorder/model/test_snmp_v2_params.py
tests/recorder/model/test_snmp_v3_params.py
tests/recorder/snmp/__init__.py
tests/recorder/snmp/test_snmp_orch.py
tests/recorder/snmp/test_snmp_recorder.py
tests/recorder/snmp/test_snmp_service.py