Metadata-Version: 1.2
Name: cloudshell-recorder
Version: 1.1.0
Summary: QualiSystems CloudShell Device Recorder Python package
Home-page: http://www.qualisystems.com/
Author: QualiSystems
Author-email: info@qualisystems.com
License: UNKNOWN
Platform: UNKNOWN
Requires-Python: >=2.7, <3.0
